{
  "drug_name": "7-(alpha-D-Glucopyranosyloxy)-4-methyl-2H-1-benzopyran-2-one",
  "generic_name": [
    "7-(alpha-D-Glucopyranosyloxy)-4-methyl-2H-1-benzopyran-2-one"
  ],
  "brand_names": [],
  "drug_interactions": [],
  "warnings": [
    "Warnings For external use only When using this product Do not get into eyes Stop use and ask a doctor if Condition worsens Symptoms last more than 7 days or clear up and occur again within a few days Do not use on Deep or puncture wounds Animal bites Serious burns Keep out of reach of children. If swallowed, get medical help or contact a Poison Control Center right away."
  ],
  "adverse_reactions": [],
  "contraindications": [],
  "dosage_administration": [
    "Directions Apply as needed."
  ],
  "indications": [
    "Uses Helps prevent and temporarily protects chafed, chapped or cracked skin"
  ],
  "fetched_at": "2025-10-01T03:05:29.889552",
  "source": "OpenFDA"
}