{
  "query": "Bictegravir",
  "results": {
    "drugGroup": {
      "name": null,
      "conceptGroup": [
        {
          "tty": "BPCK"
        },
        {
          "tty": "GPCK"
        },
        {
          "tty": "SBD",
          "conceptProperties": [
            {
              "rxcui": "1999673",
              "name": "bictegravir 50 MG / emtricitabine 200 MG / tenofovir alafenamide 25 MG Oral Tablet [Biktarvy]",
              "synonym": "Biktarvy 50 MG / 200 MG / 25 MG Oral Tablet",
              "tty": "SBD",
              "language": "ENG",
              "suppress": "N",
              "umlscui": ""
            },
            {
              "rxcui": "2584356",
              "name": "bictegravir 30 MG / emtricitabine 120 MG / tenofovir alafenamide 15 MG Oral Tablet [Biktarvy]",
              "synonym": "Biktarvy 30 MG / 120 MG / 15 MG Oral Tablet",
              "tty": "SBD",
              "language": "ENG",
              "suppress": "N",
              "umlscui": ""
            }
          ]
        },
        {
          "tty": "SCD",
          "conceptProperties": [
            {
              "rxcui": "1999667",
              "name": "bictegravir 50 MG / emtricitabine 200 MG / tenofovir alafenamide 25 MG Oral Tablet",
              "synonym": "bictegravir 50 MG (as bictegravir sodium 52.5 MG) / emtricitabine 200 MG / tenofovir alafenamide 25 MG (as tenofovir alafenamide fumarate 28 MG) Oral Tablet",
              "tty": "SCD",
              "language": "ENG",
              "suppress": "N",
              "umlscui": ""
            },
            {
              "rxcui": "2584354",
              "name": "bictegravir 30 MG / emtricitabine 120 MG / tenofovir alafenamide 15 MG Oral Tablet",
              "synonym": "bictegravir 30 MG (as bictegravir sodium 31.5 MG) / emtricitabine 120 MG / tenofovir alafenamide 15 MG (as tenofovir alafenamide fumarate 16.5 MG) Oral Tablet",
              "tty": "SCD",
              "language": "ENG",
              "suppress": "N",
              "umlscui": ""
            }
          ]
        }
      ]
    }
  },
  "fetched_at": "2025-10-01T18:21:09.375232",
  "source": "RxNorm"
}