{
  "query": "Robenacoxib",
  "results": {
    "drugGroup": {
      "name": null,
      "conceptGroup": [
        {
          "tty": "BPCK"
        },
        {
          "tty": "GPCK"
        },
        {
          "tty": "SBD",
          "conceptProperties": [
            {
              "rxcui": "1250214",
              "name": "robenacoxib 6 MG Oral Tablet [Onsior]",
              "synonym": "Onsior 6 MG Oral Tablet",
              "tty": "SBD",
              "language": "ENG",
              "suppress": "N",
              "umlscui": ""
            },
            {
              "rxcui": "1664300",
              "name": "robenacoxib 20 MG/ML Injectable Solution [Onsior]",
              "synonym": "Onsior 20 MG/ML Injectable Solution",
              "tty": "SBD",
              "language": "ENG",
              "suppress": "N",
              "umlscui": ""
            }
          ]
        },
        {
          "tty": "SCD",
          "conceptProperties": [
            {
              "rxcui": "1250208",
              "name": "robenacoxib 6 MG Oral Tablet",
              "synonym": "",
              "tty": "SCD",
              "language": "ENG",
              "suppress": "N",
              "umlscui": ""
            },
            {
              "rxcui": "1664296",
              "name": "robenacoxib 20 MG/ML Injectable Solution",
              "synonym": "",
              "tty": "SCD",
              "language": "ENG",
              "suppress": "N",
              "umlscui": ""
            }
          ]
        }
      ]
    }
  },
  "fetched_at": "2025-10-01T18:01:50.046134",
  "source": "RxNorm"
}